eloquaformhandler/__init__.py
eloquaformhandler/dataclass.py
eloquaformhandler/exceptions.py
eloquaformhandler/handler.py
eloqua_formhandler-0.9a1.dist-info/LICENSE.txt
eloqua_formhandler-0.9a1.dist-info/METADATA
eloqua_formhandler-0.9a1.dist-info/WHEEL
eloqua_formhandler-0.9a1.dist-info/top_level.txt
eloqua_formhandler-0.9a1.dist-info/RECORD
