Metadata-Version: 2.1
Name: eloqua-formhandler
Version: 0.9a1
Summary: Validate and send Oracle Eloqua Forms.
Home-page: https://gitlab.com/intheflow/python-eloqua-formhandler
Author: Florian Schweikert
Author-email: florian.schweikert@zumtobelgroup.com
License: MIT License
Keywords: eloqua
Platform: UNKNOWN
Classifier: Development Status :: 3 - Alpha
Classifier: Intended Audience :: Developers
Classifier: License :: OSI Approved :: MIT License
Classifier: Operating System :: OS Independent
Classifier: Programming Language :: Python :: 3.6
Classifier: Programming Language :: Python :: 3.7
Requires-Dist: requests
Requires-Dist: structlog
Requires-Dist: attrs
